hdsemg_select/__init__.py
hdsemg_select/hdsemg-select-macos.spec
hdsemg_select/hdsemg-select-win.spec
hdsemg_select/main.py
hdsemg_select/make_version.py
hdsemg_select/resources.qrc
hdsemg_select/resources_rc.py
hdsemg_select/version.py
hdsemg_select/_log/__init__.py
hdsemg_select/_log/exception_hook.py
hdsemg_select/_log/log_config.py
hdsemg_select/config/__init__.py
hdsemg_select/config/config_enums.py
hdsemg_select/config/config_manager.py
hdsemg_select/controller/__init__.py
hdsemg_select/controller/file_management.py
hdsemg_select/controller/grid_setup_handler.py
hdsemg_select/controller/menu_manager.py
hdsemg_select/helper/__init__.py
hdsemg_select/helper/otbscraper.py
hdsemg_select/resources/extend.png
hdsemg_select/resources/frequency.png
hdsemg_select/resources/icon.icns
hdsemg_select/resources/icon.ico
hdsemg_select/resources/icon.png
hdsemg_select/resources/icon.svg
hdsemg_select/resources/settings.png
hdsemg_select/select_logic/__init__.py
hdsemg_select/select_logic/auto_flagger.py
hdsemg_select/select_logic/channel_management.py
hdsemg_select/select_logic/data_processing.py
hdsemg_select/select_logic/plotting.py
hdsemg_select/settings/__init__.py
hdsemg_select/settings/settings_dialog.py
hdsemg_select/settings/tabs/__init__.py
hdsemg_select/settings/tabs/auto_flagger_settings_tab.py
hdsemg_select/settings/tabs/custom_flagger_settings_tab.py
hdsemg_select/settings/tabs/log_setting.py
hdsemg_select/state/__init__.py
hdsemg_select/state/state.py
hdsemg_select/state/enum/__init__.py
hdsemg_select/state/enum/layout_mode_enums.py
hdsemg_select/ui/__init__.py
hdsemg_select/ui/main_window.py
hdsemg_select/ui/dialog/__init__.py
hdsemg_select/ui/dialog/channel_details.py
hdsemg_select/ui/dialog/channel_spectrum.py
hdsemg_select/ui/dialog/differential_filter_settings_dialog.py
hdsemg_select/ui/dialog/grid_orientation_dialog.py
hdsemg_select/ui/dialog/manual_grid_input.py
hdsemg_select/ui/icons/__init__.py
hdsemg_select/ui/icons/custom_icon_enum.py
hdsemg_select-0.1.1.dist-info/METADATA
hdsemg_select-0.1.1.dist-info/WHEEL
hdsemg_select-0.1.1.dist-info/entry_points.txt
hdsemg_select-0.1.1.dist-info/top_level.txt
hdsemg_select-0.1.1.dist-info/RECORD
