Metadata-Version: 2.4
Name: hdsemg-select
Version: 0.1.1
Summary: hdsemg-select package
Home-page: https://github.com/johanneskasser/hdsemg-select
Author: Johannes Kasser
Author-email: johanneskasser@outlook.de
Classifier: Programming Language :: Python :: 3
Classifier: License :: OSI Approved :: MIT License
Classifier: Operating System :: OS Independent
Requires-Python: >=3.7
Requires-Dist: PyQt5>=5.15.0
Requires-Dist: pyqt5-tools>=5.15.9.3.3; sys_platform == "win32"
Requires-Dist: matplotlib>=3.4.0
Requires-Dist: numpy>=1.21.0
Requires-Dist: scipy>=1.7.0
Requires-Dist: requests>=2.30.0
Requires-Dist: hdsemg-shared>=0.11.1
Requires-Dist: pefile>=2023.2.7; sys_platform != "win32"
Dynamic: author
Dynamic: author-email
Dynamic: classifier
Dynamic: description
Dynamic: description-content-type
Dynamic: home-page
Dynamic: requires-dist
Dynamic: requires-python
Dynamic: summary
